<odoo>
    <data>
        <template id="portal_my_member_memberships" name="My member memberships">
            <t t-call="portal.portal_layout">
                <t t-set="breadcrumbs_searchbar" t-value="True"/>

                <t t-call="portal.portal_searchbar">
                    <t t-set="title">Memberships</t>
                </t>
                <t t-if="not member_memberships">
                    <p>There are currently no memberships.</p>
                </t>

                <t t-if="member_memberships" t-call="portal.portal_table">
                    <thead>
                        <tr class="active">
                            <th class="text-right">ID</th>
                            <th class="text-right">Membership</th>
                            <th class="text-right">Membership due date start</th>
                            <th class="text-right">Membership due date</th>
                            <th class="text-right">Status</th>
                        </tr>
                    </thead>
                    <t t-foreach="member_memberships" t-as="mm">
                        <tr>
                            <td class="text-right">
                                <span t-field="mm.name"/>
                            </td>
                            <td class="text-right">
                                <span t-field="mm.membership_id.name"/>
                            </td>
                            <td class="text-right">
                                <span t-field="mm.initial_due_date"/>
                            </td>
                            <td class="text-right">
                                <span t-field="mm.current_due_date"/>
                            </td>
                            <td class="text-center">

                                <t t-if="mm.state == 'cancel'">
                                     <span class="badge badge-pill badge-danger">
                                            <i class="fa fa-fw fa-times" aria-label="Paid" title="Active" role="img"></i>
                                            <span class="d-none d-md-inline"> <span t-field="mm.state"/></span>
                                     </span>
                                </t>
                                <t t-if="mm.state == 'pending' or mm.state == 'overdue'">
                                     <span class="badge badge-pill badge-warning">
                                            <i class="fa fa-fw fa-times" aria-label="Paid" title="Pending" role="img"></i>
                                            <span class="d-none d-md-inline"> <span t-field="mm.state"/></span>
                                     </span>
                                </t>

                                <t t-if="mm.state == 'active'">
                                     <span class="badge badge-pill badge-success">
                                            <i class="fa fa-fw fa-check" aria-label="Paid" title="Active" role="img"></i>
                                            <span class="d-none d-md-inline"> <span t-field="mm.state"/></span>
                                     </span>
                                </t>
                            </td>

                        </tr>
                    </t>
                </t>

            </t>
        </template>


    </data>
</odoo>
